{"version":1,"resource":"vscode-remote://el1909-bavariancristusp-2exs9z2egnt.ws-eu98.gitpod.io/workspace/bavarian-cristus-PP4/templates/index.html","entries":[{"id":"B9n2.html","timestamp":1685094288000},{"id":"aOLJ.html","timestamp":1685094305804},{"id":"mixN.html","timestamp":1685094336640},{"id":"CGgF.html","timestamp":1685094347172},{"id":"Rgqu.html","timestamp":1685094453348},{"id":"TnnF.html","timestamp":1685095975322},{"id":"sGbd.html","timestamp":1685096222470},{"id":"rzKf.html","timestamp":1685096457866},{"id":"yfVI.html","timestamp":1685097037938},{"id":"UatU.html","source":"undoRedo.source","timestamp":1685097057778},{"id":"Bf2E.html","timestamp":1685429660712},{"id":"SY8H.html","timestamp":1685430061956},{"id":"o2ex.html","timestamp":1685430111688},{"id":"KdHr.html","timestamp":1685453040586},{"id":"4Ios.html","timestamp":1685453129130},{"id":"gC0g.html","timestamp":1685525334669},{"id":"RHMw.html","timestamp":1685526513393},{"id":"z6SC.html","timestamp":1685611680037},{"id":"AJbx.html","timestamp":1685611880188},{"id":"Q4nI.html","timestamp":1685611897248},{"id":"DvzX.html","timestamp":1685612063648},{"id":"cFVu.html","timestamp":1685613180248},{"id":"38yE.html","timestamp":1685613301196},{"id":"xAh8.html","timestamp":1685613353480},{"id":"HwpP.html","timestamp":1685613560672},{"id":"tfKo.html","timestamp":1685613668620},{"id":"xSSv.html","timestamp":1685613692012},{"id":"4sDQ.html","timestamp":1685613723560},{"id":"f2TO.html","timestamp":1685613759636},{"id":"QR0d.html","timestamp":1685613813480},{"id":"3hBu.html","timestamp":1685613828392},{"id":"oAjE.html","timestamp":1685693984536},{"id":"vQuv.html","timestamp":1685694012064},{"id":"xQfD.html","timestamp":1685697920160},{"id":"xO1i.html","timestamp":1685917979723},{"id":"3xpl.html","timestamp":1685918980998},{"id":"BK3C.html","timestamp":1685919087278},{"id":"31Cj.html","timestamp":1685919689001},{"id":"STXb.html","timestamp":1685923712837},{"id":"xXQq.html","timestamp":1685923739781},{"id":"7aY8.html","timestamp":1685923811857},{"id":"Q2eb.html","timestamp":1685923828169},{"id":"i7Uj.html","timestamp":1685923857413},{"id":"HAJG.html","timestamp":1685923941729},{"id":"NEFS.html","timestamp":1685924174069},{"id":"C79n.html","timestamp":1685924468577},{"id":"lpt6.html","timestamp":1685924634925},{"id":"TtSC.html","source":"undoRedo.source","timestamp":1685924648605},{"id":"50G8.html","timestamp":1685924678297},{"id":"yOth.html","timestamp":1685926652483}]}